Workbook

Sheet Summary
A1: Agent (Sales Partner) Flow - Deep Test Cases: Execution Summary
A2: Status counts are formulas over each section sheet's Status column. Update Status there; this page recalculates.
A4: Section | B4: Sheet | C4: Total | D4: Not Run | E4: Pass | F4: Fail | G4: Blocked | H4: N/A | I4: % Pass
A5: 1. Referral link / cookie capture | B5: 1 Referral link cookie capt | C5: =COUNTA('1 Referral link cookie capt'!$A$2:$A$14) | D5: =COUNTIF('1 Referral link cookie capt'!$F$2:$F$14,"Not Run") | E5: =COUNTIF('1 Referral link cookie capt'!$F$2:$F$14,"Pass") | F5: =COUNTIF('1 Referral link cookie capt'!$F$2:$F$14,"Fail") | G5: =COUNTIF('1 Referral link cookie capt'!$F$2:$F$14,"Blocked") | H5: =COUNTIF('1 Referral link cookie capt'!$F$2:$F$14,"N/A") | I5: =IF(C5-H5=0,0,E5/(C5-H5))
A6: 2. Customer assignment (R1, R2, R3) | B6: 2 Customer assignment (R1, R | C6: =COUNTA('2 Customer assignment (R1, R'!$A$2:$A$17) | D6: =COUNTIF('2 Customer assignment (R1, R'!$F$2:$F$17,"Not Run") | E6: =COUNTIF('2 Customer assignment (R1, R'!$F$2:$F$17,"Pass") | F6: =COUNTIF('2 Customer assignment (R1, R'!$F$2:$F$17,"Fail") | G6: =COUNTIF('2 Customer assignment (R1, R'!$F$2:$F$17,"Blocked") | H6: =COUNTIF('2 Customer assignment (R1, R'!$F$2:$F$17,"N/A") | I6: =IF(C6-H6=0,0,E6/(C6-H6))
A7: 3. Admin transfer (R11) | B7: 3 Admin transfer (R11) | C7: =COUNTA('3 Admin transfer (R11)'!$A$2:$A$22) | D7: =COUNTIF('3 Admin transfer (R11)'!$F$2:$F$22,"Not Run") | E7: =COUNTIF('3 Admin transfer (R11)'!$F$2:$F$22,"Pass") | F7: =COUNTIF('3 Admin transfer (R11)'!$F$2:$F$22,"Fail") | G7: =COUNTIF('3 Admin transfer (R11)'!$F$2:$F$22,"Blocked") | H7: =COUNTIF('3 Admin transfer (R11)'!$F$2:$F$22,"N/A") | I7: =IF(C7-H7=0,0,E7/(C7-H7))
A8: 4. Agent customer list & isolation | B8: 4 Agent customer list & isol | C8: =COUNTA('4 Agent customer list & isol'!$A$2:$A$11) | D8: =COUNTIF('4 Agent customer list & isol'!$E$2:$E$11,"Not Run") | E8: =COUNTIF('4 Agent customer list & isol'!$E$2:$E$11,"Pass") | F8: =COUNTIF('4 Agent customer list & isol'!$E$2:$E$11,"Fail") | G8: =COUNTIF('4 Agent customer list & isol'!$E$2:$E$11,"Blocked") | H8: =COUNTIF('4 Agent customer list & isol'!$E$2:$E$11,"N/A") | I8: =IF(C8-H8=0,0,E8/(C8-H8))
A9: 5. Agent-placed order (R9, R10) | B9: 5 Agent-placed order (R9, R1 | C9: =COUNTA('5 Agent-placed order (R9, R1'!$A$2:$A$48) | D9: =COUNTIF('5 Agent-placed order (R9, R1'!$E$2:$E$48,"Not Run") | E9: =COUNTIF('5 Agent-placed order (R9, R1'!$E$2:$E$48,"Pass") | F9: =COUNTIF('5 Agent-placed order (R9, R1'!$E$2:$E$48,"Fail") | G9: =COUNTIF('5 Agent-placed order (R9, R1'!$E$2:$E$48,"Blocked") | H9: =COUNTIF('5 Agent-placed order (R9, R1'!$E$2:$E$48,"N/A") | I9: =IF(C9-H9=0,0,E9/(C9-H9))
A10: 6. Commission creation (R4) | B10: 6 Commission creation (R4) | C10: =COUNTA('6 Commission creation (R4)'!$A$2:$A$20) | D10: =COUNTIF('6 Commission creation (R4)'!$E$2:$E$20,"Not Run") | E10: =COUNTIF('6 Commission creation (R4)'!$E$2:$E$20,"Pass") | F10: =COUNTIF('6 Commission creation (R4)'!$E$2:$E$20,"Fail") | G10: =COUNTIF('6 Commission creation (R4)'!$E$2:$E$20,"Blocked") | H10: =COUNTIF('6 Commission creation (R4)'!$E$2:$E$20,"N/A") | I10: =IF(C10-H10=0,0,E10/(C10-H10))
A11: 7. Commission lifecycle (R5, R6) | B11: 7 Commission lifecycle (R5, | C11: =COUNTA('7 Commission lifecycle (R5, '!$A$2:$A$27) | D11: =COUNTIF('7 Commission lifecycle (R5, '!$E$2:$E$27,"Not Run") | E11: =COUNTIF('7 Commission lifecycle (R5, '!$E$2:$E$27,"Pass") | F11: =COUNTIF('7 Commission lifecycle (R5, '!$E$2:$E$27,"Fail") | G11: =COUNTIF('7 Commission lifecycle (R5, '!$E$2:$E$27,"Blocked") | H11: =COUNTIF('7 Commission lifecycle (R5, '!$E$2:$E$27,"N/A") | I11: =IF(C11-H11=0,0,E11/(C11-H11))
A12: 8. Payout (R7, R8) | B12: 8 Payout (R7, R8) | C12: =COUNTA('8 Payout (R7, R8)'!$A$2:$A$30) | D12: =COUNTIF('8 Payout (R7, R8)'!$E$2:$E$30,"Not Run") | E12: =COUNTIF('8 Payout (R7, R8)'!$E$2:$E$30,"Pass") | F12: =COUNTIF('8 Payout (R7, R8)'!$E$2:$E$30,"Fail") | G12: =COUNTIF('8 Payout (R7, R8)'!$E$2:$E$30,"Blocked") | H12: =COUNTIF('8 Payout (R7, R8)'!$E$2:$E$30,"N/A") | I12: =IF(C12-H12=0,0,E12/(C12-H12))
A13: 9. Agent profile, KYC & bank (touchpoints with payout) | B13: 9 Agent profile, KYC & bank | C13: =COUNTA('9 Agent profile, KYC & bank '!$A$2:$A$12) | D13: =COUNTIF('9 Agent profile, KYC & bank '!$E$2:$E$12,"Not Run") | E13: =COUNTIF('9 Agent profile, KYC & bank '!$E$2:$E$12,"Pass") | F13: =COUNTIF('9 Agent profile, KYC & bank '!$E$2:$E$12,"Fail") | G13: =COUNTIF('9 Agent profile, KYC & bank '!$E$2:$E$12,"Blocked") | H13: =COUNTIF('9 Agent profile, KYC & bank '!$E$2:$E$12,"N/A") | I13: =IF(C13-H13=0,0,E13/(C13-H13))
A14: 10. Admin agent management | B14: 10 Admin agent management | C14: =COUNTA('10 Admin agent management'!$A$2:$A$14) | D14: =COUNTIF('10 Admin agent management'!$E$2:$E$14,"Not Run") | E14: =COUNTIF('10 Admin agent management'!$E$2:$E$14,"Pass") | F14: =COUNTIF('10 Admin agent management'!$E$2:$E$14,"Fail") | G14: =COUNTIF('10 Admin agent management'!$E$2:$E$14,"Blocked") | H14: =COUNTIF('10 Admin agent management'!$E$2:$E$14,"N/A") | I14: =IF(C14-H14=0,0,E14/(C14-H14))
A15: 11. Authorization matrix (API) | B15: 11 Authorization matrix (API | C15: =COUNTA('11 Authorization matrix (API'!$A$2:$A$15) | D15: =COUNTIF('11 Authorization matrix (API'!$D$2:$D$15,"Not Run") | E15: =COUNTIF('11 Authorization matrix (API'!$D$2:$D$15,"Pass") | F15: =COUNTIF('11 Authorization matrix (API'!$D$2:$D$15,"Fail") | G15: =COUNTIF('11 Authorization matrix (API'!$D$2:$D$15,"Blocked") | H15: =COUNTIF('11 Authorization matrix (API'!$D$2:$D$15,"N/A") | I15: =IF(C15-H15=0,0,E15/(C15-H15))
A16: 12. Agent dashboard & lists | B16: 12 Agent dashboard & lists | C16: =COUNTA('12 Agent dashboard & lists'!$A$2:$A$13) | D16: =COUNTIF('12 Agent dashboard & lists'!$E$2:$E$13,"Not Run") | E16: =COUNTIF('12 Agent dashboard & lists'!$E$2:$E$13,"Pass") | F16: =COUNTIF('12 Agent dashboard & lists'!$E$2:$E$13,"Fail") | G16: =COUNTIF('12 Agent dashboard & lists'!$E$2:$E$13,"Blocked") | H16: =COUNTIF('12 Agent dashboard & lists'!$E$2:$E$13,"N/A") | I16: =IF(C16-H16=0,0,E16/(C16-H16))
A17: 13. End-to-end journeys (run in this order on a clean DB) | B17: 13 End-to-end journeys (run | C17: =COUNTA('13 End-to-end journeys (run '!$A$2:$A$10) | D17: =COUNTIF('13 End-to-end journeys (run '!$C$2:$C$10,"Not Run") | E17: =COUNTIF('13 End-to-end journeys (run '!$C$2:$C$10,"Pass") | F17: =COUNTIF('13 End-to-end journeys (run '!$C$2:$C$10,"Fail") | G17: =COUNTIF('13 End-to-end journeys (run '!$C$2:$C$10,"Blocked") | H17: =COUNTIF('13 End-to-end journeys (run '!$C$2:$C$10,"N/A") | I17: =IF(C17-H17=0,0,E17/(C17-H17))
A18: TOTAL | C18: =SUM(C5:C17) | D18: =SUM(D5:D17) | E18: =SUM(E5:E17) | F18: =SUM(F5:F17) | G18: =SUM(G5:G17) | H18: =SUM(H5:H17) | I18: =IF(C18-H18=0,0,E18/(C18-H18))
A20: Priority: P0 = money / data ownership, P1 = core flow, P2 = edge / UX. Source: docs/agent-flow-deep-test-cases.md (derived from current code).

Sheet 0 Rules
A1: # | B1: Rule | C1: Source
A2: R1 | B2: A customer has ONE current_agent_id. Referral code only fills an empty slot; a different code never changes it. Only admin transfer moves it. | C2: customer-assignment.service.ts
A3: R2 | B3: Order attribution is frozen at order creation: customer-with-agent → CUSTOMER_DIRECT + that agent; agent buying for self → AGENT_OWN (earns commission); agent placing for customer → AGENT_PLACED_FOR_CUSTOMER. | C3: resolveOrderAttribution, agent-order.service.ts
A4: R3 | B4: Inactive/deleted agent is not credited (order gets no agent) – but customer's current_agent_id is NOT cleared. | C4: resolveOrderAttribution
A5: R4 | B5: Commission per order item on total_price (after item offers, excl. shipping). Rate: product → category (walk up parents) → global → 0 (no row). Rate ≤ 0 or item amount ≤ 0 ⇒ no commission row. % and amount frozen. | C5: commission.service.ts
A6: R5 | B6: delivered starts return period (setting, default 3 days). Approval is lazy (on read / payout request / admin "approve eligible"), batch of 500. | C6: approveEligible
A7: R6 | B7: cancelled: pending → cancelled; approved/in-payout → reversed. returned → always reversed. Paid + reversed → clawback_due=true. In-payout reversed commission is pulled out, payout amount recalculated; if 0 → payout cancelled. | C7: voidCommissions
A8: R7 | B8: Payout takes all approved un-requested commissions. Method must be upi/bank_transfer with saved profile data (snapshotted on payout). | C8: payout.service.ts
A9: R8 | B9: Payout transitions: requested→approved→paid; reject allowed from requested/approved (commissions back to approved); paid cannot be rejected. | C9: payout.service.ts
A10: R9 | B10: Agent-placed order: payment = COD, pending, status = confirmed. Price/stock/offers from DB, never from payload. Duplicate lines for same SKU are merged. | C10: agent-order.service.ts
A11: R10 | B11: Agent-placed order input: exactly one of customerId / manualCustomer. Qty 1–999, max 50 lines, notes ≤ 500. | C11: agent-order.schema.ts
A12: R11 | B12: Transfer: admin only; destination must be active agent; stale fromAgentRef ⇒ 409; same agent ⇒ 400; history never deleted. | C12: transferCustomer

Sheet 1 Referral link  cookie capt
A1: ID | B1: P | C1: Scenario | D1: Steps | E1: Expected | F1: Status | G1: Tester | H1: Date | I1: Remarks
A2: AF-001 | B2: P0 | C2: Valid link on home | D2: Open /?ref=AGT001 (incognito) | E2: Cookie referral_agent set (HttpOnly, SameSite=Lax, ~30d) | F2: Not Run
A3: AF-002 | B3: P1 | C3: Valid link on deep page | D3: /products/xyz?ref=AGT001 | E3: Cookie set; page loads normally | F3: Not Run
A4: AF-003 | B4: P1 | C4: /ref/AGT001 short path | D4: Open it | E4: Redirects, cookie set | F4: Not Run
A5: AF-004 | B5: P1 | C5: Lowercase code ?ref=agt001 | D5: Open | E5: Check: matches or not – document actual behaviour (DB collation) | F5: Not Run
A6: AF-005 | B6: P1 | C6: Invalid format ?ref=a , ?ref=<script>, ?ref=A B, 31 chars | D6: Open each | E6: No cookie stored, no error shown | F6: Not Run
A7: AF-006 | B7: P1 | C7: Valid format but nonexistent code ?ref=ZZZ999 | D7: Open; call GET /api/referral/validate?code=ZZZ999 | E7: Cookie may store; validate returns invalid; no assignment later | F7: Not Run
A8: AF-007 | B8: P1 | C8: Inactive agent code | D8: Deactivate agent, open link, register | E8: Customer not assigned | F8: Not Run
A9: AF-008 | B9: P1 | C9: Last link wins in cookie | D9: Open A link, then B link | E9: Cookie = B | F9: Not Run
A10: AF-009 | B10: P1 | C10: GET /api/referral/current | D10: With / without cookie | E10: Returns agent name for valid, empty for none; no sensitive data (no email/phone) | F10: Not Run
A11: AF-010 | B11: P1 | C11: Applied-referral banner | D11: Open link | E11: AppliedReferral shows correct agent; hides on invalid | F11: Not Run
A12: AF-011 | B12: P2 | C12: Cookie expiry | D12: Edit cookie to expired | E12: Behaves as no referral | F12: Not Run
A13: AF-012 | B13: P2 | C13: Cookie tamper | D13: Set cookie to ' OR 1=1-- | E13: Ignored, no 500 | F13: Not Run
A14: AF-013 | B14: P1 | C14: Agent code vs referral code | D14: Use agent_code and referral_code of same agent | E14: Both resolve to the same agent | F14: Not Run

Sheet 2 Customer assignment (R1, R
A1: ID | B1: P | C1: Scenario | D1: Steps | E1: Expected | F1: Status | G1: Tester | H1: Date | I1: Remarks
A2: AF-020 | B2: P0 | C2: New signup via A link | D2: Link A → register | E2: current_agent_id=A, agent_assigned_at set, history row assigned / "Referral code", audit customer_assigned | F2: Not Run
A3: AF-021 | B3: P0 | C3: New signup without link | D3: Register plain | E3: No agent, no history row | F3: Not Run
A4: AF-022 | B4: P0 | C4: Existing unassigned customer, login via A link | D4: Login after opening link | E4: Assigned A (verify where: login or first order – note which) | F4: Not Run
A5: AF-023 | B5: P0 | C5: Unassigned customer places order with A cookie | D5: Checkout | E5: Assigned A and order.agent_id = A in same transaction | F5: Not Run
A6: AF-024 | B6: P0 | C6: Assigned to A, B cookie, place order | D6: Checkout | E6: Stays A; order agent = A; B gets nothing | F6: Not Run
A7: AF-025 | B7: P0 | C7: Assigned to A, no cookie, order | D7: Checkout | E7: Order agent = A (assignment not cookie-dependent) | F7: Not Run
A8: AF-026 | B8: P0 | C8: Race: two tabs, A link and B link, unassigned customer orders in both at same time | D8: Fire 2 checkouts concurrently | E8: Exactly one agent wins; assigned history has 1 row; both orders attributed to the same agent | F8: Not Run
A9: AF-027 | B9: P0 | C9: Agent opens another agent's link and logs in | D9: Login agent A with B cookie | E9: A not assigned to anyone (role ≠ customer) | F9: Not Run
A10: AF-028 | B10: P0 | C10: Agent shops for self | D10: Agent A logs in, orders on storefront | E10: AGENT_OWN, agent=A, commission rows created (R2) | F10: Not Run
A11: AF-029 | B11: P0 | C11: Customer's agent deactivated | D11: C→A, admin deactivates A, C orders with B's cookie | E11: Order has no agent (R3), C still shows A (stuck). Confirm admin can transfer to B. Flag as product decision | F11: Not Run
A12: AF-030 | B12: P1 | C12: Agent reactivated | D12: Reactivate A, C orders | E12: Credited to A again | F12: Not Run
A13: AF-031 | B13: P1 | C13: Agent soft-deleted | D13: Delete A | E13: Customers keep pointer, orders no agent, no crash on admin customer page | F13: Not Run
... A17: AF-035 | B17: P2 | C17: Account deleted/re-registered same email | D17: Register again with other link | E17: Treated as new customer (check unique soft-delete values) | F17: Not Run

Sheet 3 Admin transfer (R11)
A1: ID | B1: P | C1: Scenario | D1: Steps | E1: Expected | F1: Status | G1: Tester | H1: Date | I1: Remarks
A2: AF-040 | B2: P0 | C2: A → B happy path | D2: Admin → customer → Sales Partner card → B → Confirm | E2: Confirm dialog; current_agent_id=B; history transferred with from/to/admin/reason; audit row | F2: Not Run
A3: AF-041 | B3: P0 | C3: Old orders untouched | D3: Check C's pre-transfer orders & commissions | E3: agent_id/commissions still A | F3: Not Run
A4: AF-042 | B4: P0 | C4: Pre-transfer pending commission of A | D4: After transfer, deliver old order | E4: Commission still credited to A, not B | F4: Not Run
A5: AF-043 | B5: P0 | C5: New order after transfer | D5: C orders | E5: agent=B | F5: Not Run
A6: AF-044 | B6: P0 | C6: Same agent | D6: A → A | E6: 400 "already assigned" | F6: Not Run
A7: AF-045 | B7: P0 | C7: Stale screen | D7: 2 tabs, transfer in tab 1, tab 2 transfer | E7: 409 "has changed. Refresh" | F7: Not Run
A8: AF-046 | B8: P0 | C8: Concurrent transfers (A→B and A→C at once) | D8: 2 API calls same fromAgentRef | E8: One 200, one 409; one history row | F8: Not Run
A9: AF-047 | B9: P0 | C9: Destination inactive / deleted | D9: Transfer to inactive B | E9: 400 "not active" | F9: Not Run
A10: AF-048 | B10: P1 | C10: Destination is not an agent (customer/admin uuid) | D10: API with customer uuid | E10: 400 "Destination not found" | F10: Not Run
A11: AF-049 | B11: P1 | C11: Unknown destination / unknown customer | D11: Random uuid | E11: 400 / 404 | F11: Not Run
A12: AF-050 | B12: P1 | C12: Customer with no agent → assign by admin | D12: Omit fromAgentRef | E12: Allowed; history action assigned; actor = admin name | F12: Not Run
A13: AF-051 | B13: P1 | C13: Omit fromAgentRef on assigned customer | D13: API | E13: Allowed (no stale protection) – confirm intended | F13: Not Run
... A22: AF-060 | B22: P2 | C22: Customer sees agent name? | D22: Customer account | E22: Agent identity not leaked unless intended | F22: Not Run

Sheet 4 Agent customer list & isol
A1: ID | B1: P | C1: Scenario | D1: Expected | E1: Status | F1: Tester | G1: Date | H1: Remarks
A2: AF-070 | B2: P0 | C2: A's list contains only current_agent_id=A customers | D2: Verify count vs DB | E2: Not Run
A3: AF-071 | B3: P1 | C3: Columns: name, customer ID, mobile, email | D3: Shown, masked as designed | E3: Not Run
A4: AF-072 | B4: P1 | C4: Search name / cust_id / mobile / email, partial, case-insensitive | D4: Correct matches; no match → empty state | E4: Not Run
A5: AF-073 | B5: P1 | C5: Search with %, _, ', emoji | D5: No SQL error, literal handling | E5: Not Run
A6: AF-074 | B6: P1 | C6: Status filter active/inactive | D6: Correct | E6: Not Run
A7: AF-075 | B7: P1 | C7: Pagination 20/page with 45 customers; page beyond last; page=0, limit=1000, limit=-1 | D7: Clamped (1..100), no 500 | E7: Not Run
A8: AF-076 | B8: P0 | C8: Agent B hits GET /api/agent/customers/<C of A>/addresses | D8: 404 / 403, no addresses leaked | E8: Not Run
A9: AF-077 | B9: P0 | C9: Agent passes ?agent=B on /api/agent/orders, /commissions, /payouts, /dashboard | D9: Ignored; own data only | E9: Not Run
A10: AF-078 | B10: P1 | C10: Mobile 375px | D10: Table scrolls, filters usable | E10: Not Run
A11: AF-079 | B11: P2 | C11: Inactive customer in list | D11: Shown with status badge, cannot be ordered for | E11: Not Run

Sheet 5 Agent-placed order (R9, R1
A1: ID | B1: P | C1: Scenario | D1: Expected | E1: Status | F1: Tester | G1: Date | H1: Remarks
A2: AF-080 | B2: P0 | C2: Assigned customer + saved address | D2: Order: userId=C, agent_id=A, ordered_by=A, source AGENT_PLACED_FOR_CUSTOMER, status confirmed, COD/pending | E2: Not Run
A3: AF-081 | B3: P0 | C3: Customer of another agent (API) | D3: 403 "not assigned to you"; no order | E3: Not Run
A4: AF-082 | B4: P0 | C4: Unassigned customer (API) | D4: 403 | E4: Not Run
A5: AF-083 | B5: P0 | C5: Inactive customer | D5: 400 "account is inactive" | E5: Not Run
A6: AF-084 | B6: P0 | C6: Both customerId and manualCustomer | D6: 400 (schema) | E6: Not Run
A7: AF-085 | B7: P0 | C7: Neither | D7: 400 | E7: Not Run
A8: AF-086 | B8: P1 | C8: Customer + shippingAddressId of another customer | D8: 400 "address not found for this customer" | E8: Not Run
A9: AF-087 | B9: P1 | C9: Soft-deleted / inactive address id | D9: 400 | E9: Not Run
A10: AF-088 | B10: P1 | C10: Customer + inline shippingAddress | D10: Order uses it; customer's saved addresses unchanged; profile unchanged | E10: Not Run
A11: AF-089 | B11: P1 | C11: Customer with neither address id nor address | D11: 400 "Select a delivery address" | E11: Not Run
A12: AF-090 | B12: P1 | C12: Customer with 0 saved addresses in UI | D12: UI prompts to enter address, not blocked | E12: Not Run
A13: AF-095 | B13: P0 | C13: Valid manual customer + address | D13: No user created; order stores name/phone/email; userId = agent; agent=A; source AGENT_PLACED | E13: Not Run
... A48: AF-138 | B48: P1 | C48: Order-catalog /api/agent/order-catalog | D48: Only active, in-stock-aware items; search/pagination; no cost price leaked | E48: Not Run

Sheet 6 Commission creation (R4)
A1: ID | B1: P | C1: Scenario | D1: Expected | E1: Status | F1: Tester | G1: Date | H1: Remarks
A2: AF-140 | B2: P0 | C2: Order with 3 items, different categories | D2: 3 commission rows, each with own %, rate_source | E2: Not Run
A3: AF-141 | B3: P0 | C3: Rate priority: product 5%, category 3%, global 1% | D3: Product wins; remove product rate → category; remove → global; remove → none/no row | E3: Not Run
A4: AF-142 | B4: P0 | C4: Child category without rate, parent has | D4: Parent rate used (walk up) | E4: Not Run
A5: AF-143 | B5: P0 | C5: Inactive rate ignored | D5: Falls to next level | E5: Not Run
A6: AF-144 | B6: P0 | C6: Rounding: ₹99.99 × 2.5% ; ₹1 × 0.5% ; ₹0.01 | D6: round(paise × bp / 10000); check sum vs order-level commission_amount | E6: Not Run
A7: AF-145 | B7: P0 | C7: Item discount applied | D7: Commission on discounted total_price, not MRP | E7: Not Run
A8: AF-146 | B8: P0 | C8: Shipping excluded | D8: Change shipping, commission unchanged | E8: Not Run
A9: AF-147 | B9: P0 | C9: Rate 0% / no rate | D9: No commission row; order.commission_amount stays 0/null | E9: Not Run
A10: AF-148 | B10: P0 | C10: Fully discounted item (amount 0) | D10: No row | E10: Not Run
A11: AF-149 | B11: P0 | C11: Change rate after order | D11: Existing rows unchanged; new order uses new rate | E11: Not Run
A12: AF-150 | B12: P0 | C12: Duplicate protection | D12: Re-run create for same order → no duplicates (unique order_item_id) | E12: Not Run
A13: AF-151 | B13: P0 | C13: Order with no agent | D13: Zero commission rows | E13: Not Run
... A15: AF-153 | B15: P1 | C15: Order-level summary | D15: commission_percentage = blended %, commission_amount = sum | E15: Not Run
A16: AF-154 | B16: P1 | C16: customer_id on commission for walk-in | D16: =agent id; reports label as walk-in, not agent | E16: Not Run
A17: AF-155 | B17: P0 | C17: Online payment order that fails / is abandoned | D17: Commission created at order creation → confirm it is cancelled when order cancelled/payment failed (no orphan pending commission) | E17: Not Run
A18: AF-156 | B18: P0 | C18: Online payment success | D18: confirmed sync updates order_status on commissions, status stays pending | E18: Not Run
A19: AF-157 | B19: P1 | C19: Audit row commission_created per item | D19: Actor SYSTEM, metadata correct | E19: Not Run
A20: AF-158 | B20: P1 | C20: Large order (50 lines) | D20: All commissions created, within time limit | E20: Not Run

Sheet 7 Commission lifecycle (R5, 
A1: ID | B1: P | C1: Scenario | D1: Expected | E1: Status | F1: Tester | G1: Date | H1: Remarks
A2: AF-160 | B2: P0 | C2: Status mirrors: confirmed → shipped → out_for_delivery | D2: commissions.order_status follows; commission status pending | E2: Not Run
A3: AF-161 | B3: P0 | C3: Delivered | D3: delivered_at set, return_period_ends_at = delivered + N days; audit return_period_started | E3: Not Run
A4: AF-162 | B4: P0 | C4: Delivered twice (re-click / replay) | D4: Return period not reset (delivered_at: null guard) | E4: Not Run
A5: AF-163 | B5: P0 | C5: Approve before period ends | D5: 0 approved | E5: Not Run
A6: AF-164 | B6: P0 | C6: Approve exactly at / 1 sec after end | D6: Approved at <= now boundary | E6: Not Run
A7: AF-165 | B7: P0 | C7: Return period = 0 days | D7: Approvable right after delivery | E7: Not Run
A8: AF-166 | B8: P1 | C8: Setting changed after delivery | D8: Old commissions keep old end date; new use new | E8: Not Run
A9: AF-167 | B9: P1 | C9: Setting invalid (abc, -1, 91) | D9: Falls back to default / rejected by settings validation | E9: Not Run
A10: AF-168 | B10: P0 | C10: Lazy approval triggers | D10: Agent opens Commissions / Dashboard / Payouts → approved; admin button also works | E10: Not Run
A11: AF-169 | B11: P1 | C11: >500 due commissions | D11: First call approves 500, second call the rest (no loss) | E11: Not Run
A12: AF-170 | B12: P0 | C12: Concurrent approve (agent page + admin button) | D12: Each commission approved once, one audit row | E12: Not Run
A13: AF-171 | B13: P0 | C13: Cancel (pending, before delivery) | D13: cancelled, cancelled_at, reason | E13: Not Run
... A27: AF-185 | B27: P0 | C27: Return period vs customer return window | D27: Return window ≤ agent return period (config sanity), else approved commission on returnable order | E27: Not Run

Sheet 8 Payout (R7, R8)
A1: ID | B1: P | C1: Scenario | D1: Expected | E1: Status | F1: Tester | G1: Date | H1: Remarks
A2: AF-190 | B2: P0 | C2: Balance = approved, un-requested only | D2: Pending/payout/paid excluded | E2: Not Run
A3: AF-191 | B3: P0 | C3: Request UPI with valid saved UPI | D3: Payout requested; all approved → payout_requested; audit per commission | E3: Not Run
A4: AF-192 | B4: P0 | C4: Request bank with full details | D4: Snapshot holder/bank/IFSC/last4 + encrypted acct no. | E4: Not Run
A5: AF-193 | B5: P0 | C5: No UPI saved, method upi | D5: 400 "Add your UPI ID…" | E5: Not Run
A6: AF-194 | B6: P0 | C6: Bank details incomplete | D6: 400 | E6: Not Run
A7: AF-195 | B7: P0 | C7: No profile row | D7: 400 "profile is incomplete" | E7: Not Run
A8: AF-196 | B8: P0 | C8: Zero approved | D8: 400 "no approved commission" | E8: Not Run
A9: AF-197 | B9: P0 | C9: Double-click / two tabs request | D9: One payout; second 400/409; no commission in two payouts | E9: Not Run
A10: AF-198 | B10: P0 | C10: Commission reversed between read and update | D10: 409 "commissions changed", no partial payout row (transaction rolled back) | E10: Not Run
A11: AF-199 | B11: P0 | C11: Method other than upi/bank_transfer | D11: 400 | E11: Not Run
A12: AF-200 | B12: P0 | C12: Profile changed after request | D12: Payout keeps snapshot of old details | E12: Not Run
A13: AF-201 | B13: P0 | C13: Admin approve | D13: approved, commissions payout_approved, reviewer + note stored | E13: Not Run
... A30: AF-218 | B30: P1 | C30: Agent deactivated with approved balance | D30: Can still be paid by admin? confirm policy | E30: Not Run

Sheet 9 Agent profile, KYC & bank 
A1: ID | B1: P | C1: Scenario | D1: Expected | E1: Status | F1: Tester | G1: Date | H1: Remarks
A2: AF-230 | B2: P1 | C2: Profile wizard steps save independently | D2: Resume where left | E2: Not Run
A3: AF-231 | B3: P1 | C3: UPI valid: a@upi, a.b-c_d@okaxis; invalid: a@, @upi, a@b1, no @, 257 chars | D3: regex ^[A-Za-z0-9.\-_]{2,256}@[A-Za-z]{2,64}$ | E3: Not Run
A4: AF-232 | B4: P1 | C4: IFSC SBIN0001234 ✓; sbin0001234, SBIN1001234, 10 chars ✗ | D4: regex ^[A-Z]{4}0[A-Z0-9]{6}$ | E4: Not Run
A5: AF-233 | B5: P1 | C5: Account no 8 ✗, 9 ✓, 18 ✓, 19 ✗, letters ✗ | E5: Not Run
A6: AF-234 | B6: P1 | C6: Holder name digits ✗, O'Brien-Rao Jr. ✓ | E6: Not Run
A7: AF-235 | B7: P0 | C7: Account number stored encrypted | D7: DB column not plaintext; last4 correct | E7: Not Run
A8: AF-236 | B8: P1 | C8: Documents upload: type (jpg/png/pdf ✓, exe/svg ✗), size limit, corrupt file | D8: Proper errors | E8: Not Run
A9: AF-237 | B9: P0 | C9: Document access: A fetches B's document URL; admin fetches | D9: A 403/404; admin ok | E9: Not Run
A10: AF-238 | B10: P1 | C10: Admin review (approve / reject KYC) → agent sees status | D10: Reflected; payout gating if KYC required – confirm | E10: Not Run
A11: AF-239 | B11: P1 | C11: Profile photo upload/replace/remove | D11: Works; old file removed | E11: Not Run
A12: AF-240 | B12: P1 | C12: Completion % card matches fields | D12: profile-completion.ts | E12: Not Run

Sheet 10 Admin agent management
A1: ID | B1: P | C1: Scenario | D1: Expected | E1: Status | F1: Tester | G1: Date | H1: Remarks
A2: AF-250 | B2: P1 | C2: Create agent (valid) | D2: User role agent + profile + unique agent_code + referral_code | E2: Not Run
A3: AF-251 | B3: P1 | C3: Duplicate email / phone (also vs soft-deleted users) | D3: Clear error; deleted users release unique values | E3: Not Run
A4: AF-252 | B4: P1 | C4: Field limits (name 2–150, pwd 8–100, notes ≤500, phone 7–20) | D4: per agent.schema.ts | E4: Not Run
A5: AF-253 | B5: P1 | C5: Edit, empty body | D5: "Nothing to update" | E5: Not Run
A6: AF-254 | B6: P0 | C6: Deactivate | D6: Cannot login (message); sessions/refresh tokens invalid; referral stops crediting; existing commissions/payouts intact | E6: Not Run
A7: AF-255 | B7: P1 | C7: Reset password | D7: Old password fails, new works, old sessions revoked | E7: Not Run
A8: AF-256 | B8: P1 | C8: Agent detail tabs: profile, orders, own purchases, commissions, payouts, customers | D8: Totals equal list sums | E8: Not Run
A9: AF-257 | B9: P1 | C9: Admin filters (agent, status, date, order source, commission status) combine correctly | E9: Not Run
A10: AF-258 | B10: P0 | C10: Admin cannot edit a commission amount/% anywhere | D10: No such endpoint | E10: Not Run
A11: AF-259 | B11: P1 | C11: Commission rates admin: create/update/deactivate for global/category/product; duplicates; % 0, 100, 100.01, negative, 2-dec precision | D11: Validation + uniqueness | E11: Not Run
A12: AF-260 | B12: P1 | C12: Commission reports (totals by agent/period) | D12: Equal to raw commission sums; excludes cancelled/reversed as designed | E12: Not Run
A13: AF-261 | B13: P1 | C13: Audit viewer for commission/payout | D13: Chronological, actor + role, from/to status | E13: Not Run
A14: AF-262 | B14: P1 | C14: Staff / limited-permission admin | D14: Only permitted pages/APIs | E14: Not Run

Sheet 11 Authorization matrix (API
A1: ID | B1: Endpoint | C1: Agent expected | D1: Status | E1: Tester | F1: Date | G1: Remarks
A2: AF-270 | B2: /api/admin/agents* (all) | C2: 403 | D2: Not Run
A3: AF-271 | B3: /api/admin/commissions*, /approve-eligible, /audit | C3: 403 | D3: Not Run
A4: AF-272 | B4: /api/admin/agent-payouts/* approve/reject/mark-paid/destination | C4: 403 | D4: Not Run
A5: AF-273 | B5: /api/admin/commission-rates*, /commission-settings, /commission-reports | C5: 403 | D5: Not Run
A6: AF-274 | B6: /api/admin/customers/:id/agent | C6: 403 | D6: Not Run
A7: AF-275 | B7: /api/admin/agent-orders | C7: 403 | D7: Not Run
A8: AF-276 | B8: /api/agent/* as customer | C8: 403 | D8: Not Run
A9: AF-277 | B9: /api/agent/* as deactivated agent (valid old token) | C9: 401/403 | D9: Not Run
A10: AF-278 | B10: IDOR: change uuids in /api/agent/orders, /customers/:uuid/addresses, /payouts | C10: Only own resources | D10: Not Run
A11: AF-279 | B11: Mass assignment: send agentId, commission_percentage, orderSource, status, paymentStatus in place-order body | C11: Ignored / rejected | D11: Not Run
A12: AF-280 | B12: CSRF: place order from foreign origin with cookie | C12: Blocked per app policy | D12: Not Run
A13: AF-281 | B13: Rate limit / brute force on place-order and payout request | C13: Throttled or at least no data corruption | D13: Not Run
... A15: AF-283 | B15: Admin pages /admin/dashboard/agents as agent | C15: Blocked | D15: Not Run

Sheet 12 Agent dashboard & lists
A1: ID | B1: P | C1: Scenario | D1: Expected | E1: Status | F1: Tester | G1: Date | H1: Remarks
A2: AF-290 | B2: P1 | C2: Dashboard KPIs: customers, orders, sales, pending/approved/paid commission, available balance | D2: Match DB aggregates | E2: Not Run
A3: AF-291 | B3: P1 | C3: Brand-new agent (no data) | D3: Zero states, no NaN/undefined | E3: Not Run
A4: AF-292 | B4: P1 | C4: Referral link card: copy, correct domain, code | D4: Link opens with cookie | E4: Not Run
A5: AF-293 | B5: P1 | C5: Orders tabs: Customer Orders / Agent Own Orders | D5: Isolated lists; source badge, "Ordered by" | E5: Not Run
A6: AF-294 | B6: P1 | C6: Order list filters (source, status, date), search by order no. | D6: Correct | E6: Not Run
A7: AF-295 | B7: P1 | C7: Order list after transfer | D7: Old orders of C still visible to A as history; new ones not | E7: Not Run
A8: AF-296 | B8: P1 | C8: Commission list filters (status, order, customer, referral code, date) | D8: Correct; empty-state | E8: Not Run
A9: AF-297 | B9: P1 | C9: Commission row shows: order, product, base, %, amount, status, return-period end | D9: Accurate; reversed shows reason | E9: Not Run
A10: AF-298 | B10: P1 | C10: Timezone: delivered at 23:59 IST / UTC boundary | D10: Return end date consistent in UI and DB | E10: Not Run
A11: AF-299 | B11: P2 | C11: Currency formatting, large numbers (₹1,00,00,000.50) | D11: No overflow | E11: Not Run
A12: AF-300 | B12: P2 | C12: Mobile/tablet layouts (375 / 768 / 1280) for all agent pages | D12: No horizontal page scroll, 44px tap targets | E12: Not Run
A13: AF-301 | B13: P2 | C13: Loading skeletons & error banners on API failure | D13: Shown, retry works | E13: Not Run

Sheet 13 End-to-end journeys (run 
A1: ID | B1: Journey | C1: Status | D1: Tester | E1: Date | F1: Remarks
A2: AF-E1 | B2: Admin creates agent A + rate (category 5%) → A completes profile (UPI) → A shares link → customer C registers via link → C orders (COD) → admin ships → delivers → wait return period → A sees approved → A requests UPI payout → admin approves → marks paid with reference → A sees Paid. Verify every status, audit row, and totals at each step. | C2: Not Run
A3: AF-E2 | B3: Same as E1 but C returns one item after delivery within period → commission reversed for that item only → payout amount smaller. | C3: Not Run
A4: AF-E3 | B4: E1 but return happens after payout paid → clawback_due visible to admin. | C4: Not Run
A5: AF-E4 | B5: C (with A) → admin transfers to B → C orders → B earns; A's old order delivered later still pays A. | C5: Not Run
A6: AF-E5 | B6: A places order for C (COD) and for walk-in W → both delivered → commissions for both → payout includes both. | C6: Not Run
A7: AF-E6 | B7: A buys for self (Agent Own) → delivered → commission earned → appears under Agent Own tab, not Customer Orders. | C7: Not Run
A8: AF-E7 | B8: Payout requested → order in it returned → payout recalculated → admin rejects remaining → agent re-requests → paid. | C8: Not Run
A9: AF-E8 | B9: Agent deactivated with pending commissions → customer orders (no credit) → admin reactivates → pending commissions still approve & pay. | C9: Not Run
A10: AF-E9 | B10: Two agents, shared catalog, concurrent stock contention + concurrent payout approvals (data integrity). | C10: Not Run

Sheet 14 Likely defects  decisions
A1: # | B1: Observation | C1: Why it matters | D1: Suggested test
A2: D1 | B2: docs/test-cases/10 and memory note say "last referral cookie wins, per-order attribution" and "agent buying earns nothing". Code now: customer keeps first agent (R1) and agent-own orders earn commission. | C2: Old test cases will fail / mislead | D2: Re-baseline docs; AF-024, AF-028
A3: D2 | B3: Deactivated agent leaves customers orphaned: order gets no agent, referral code of a new agent can't fill the slot. | C3: Lost commission/ownership silently | D3: AF-029
A4: D3 | B4: placeOrder does not itself check agent is active | C4: Relies on auth layer | D4: AF-137, AF-277
A5: D4 | B5: Commission created at order creation, before online payment succeeds | C5: Orphan pending commission if payment fails | D5: AF-155
A6: D5 | B6: approveEligible takes 500 per call and is lazy | C6: Backlog may need several triggers | D6: AF-169
A7: D6 | B7: Transfer without fromAgentRef skips stale-screen protection | C7: Admin API misuse overwrites | D7: AF-051
A8: D7 | B8: Agent-placed orders hard-coded COD/pending | C8: No online-pay option; payment collection tracking? | D8: AF-080, confirm requirement
A9: D8 | B9: Partial-qty returns: whole item commission vs proportional | C9: Over/under-paying agents | D9: AF-175
A10: D9 | B10: No minimum payout / no KYC gating in requestPayout | C10: Possible policy gap | D10: AF-217, AF-238
A11: D10 | B11: resolveAgentRef doesn't filter deleted/inactive agents (callers do) | C11: Filters on deleted agent may still resolve | D11: AF-249/AF-047
A12: D11 | B12: Walk-in orders store userId = agent and commission customer_id = agent | C12: Reports/“Customers” counts may misattribute | D12: AF-099, AF-154
A13: D12 | B13: Return window vs return period (default 3 days) | C13: Approved commission on still-returnable order → clawback | D13: AF-185
